{"nodes": [{"id": "c_users_10954_desktop_mbforge_src_mbforge_model_server_models_moldet_py", "label": "moldet.py", "file_type": "code", "source_file": "src/mbforge/model_server/models/moldet.py", "source_location": "L1"}, {"id": "models_moldet_get_moldet", "label": "get_moldet()", "file_type": "code", "source_file": "src/mbforge/model_server/models/moldet.py", "source_location": "L14"}, {"id": "molimagepipeline", "label": "MolImagePipeline", "file_type": "code", "source_file": "src/mbforge/model_server/models/moldet.py", "source_location": "L14"}, {"id": "models_moldet_reset_moldet", "label": "reset_moldet()", "file_type": "code", "source_file": "src/mbforge/model_server/models/moldet.py", "source_location": "L25"}], "edges": [{"source": "c_users_10954_desktop_mbforge_src_mbforge_model_server_models_moldet_py", "target": "typing", "relation": "imports_from", "context": "import", "confidence": "EXTRACTED", "source_file": "src/mbforge/model_server/models/moldet.py", "source_location": "L5", "weight": 1.0}, {"source": "c_users_10954_desktop_mbforge_src_mbforge_model_server_models_moldet_py", "target": "mbforge_parsers_molecule_mol_image_pipeline", "relation": "imports_from", "context": "import", "confidence": "EXTRACTED", "source_file": "src/mbforge/model_server/models/moldet.py", "source_location": "L7", "weight": 1.0}, {"source": "c_users_10954_desktop_mbforge_src_mbforge_model_server_models_moldet_py", "target": "mbforge_utils_config", "relation": "imports_from", "context": "import", "confidence": "EXTRACTED", "source_file": "src/mbforge/model_server/models/moldet.py", "source_location": "L8", "weight": 1.0}, {"source": "c_users_10954_desktop_mbforge_src_mbforge_model_server_models_moldet_py", "target": "mbforge_utils_gpu", "relation": "imports_from", "context": "import", "confidence": "EXTRACTED", "source_file": "src/mbforge/model_server/models/moldet.py", "source_location": "L9", "weight": 1.0}, {"source": "c_users_10954_desktop_mbforge_src_mbforge_model_server_models_moldet_py", "target": "models_moldet_get_moldet", "relation": "contains", "confidence": "EXTRACTED", "source_file": "src/mbforge/model_server/models/moldet.py", "source_location": "L14", "weight": 1.0}, {"source": "models_moldet_get_moldet", "target": "molimagepipeline", "relation": "references", "context": "return_type", "confidence": "EXTRACTED", "source_file": "src/mbforge/model_server/models/moldet.py", "source_location": "L14", "weight": 1.0}, {"source": "c_users_10954_desktop_mbforge_src_mbforge_model_server_models_moldet_py", "target": "models_moldet_reset_moldet", "relation": "contains", "confidence": "EXTRACTED", "source_file": "src/mbforge/model_server/models/moldet.py", "source_location": "L25", "weight": 1.0}, {"source": "models_moldet_get_moldet", "target": "molimagepipeline", "relation": "calls", "context": "call", "confidence": "EXTRACTED", "source_file": "src/mbforge/model_server/models/moldet.py", "source_location": "L21", "weight": 1.0}], "raw_calls": [{"caller_nid": "models_moldet_get_moldet", "callee": "is_gpu_available", "is_member_call": false, "source_file": "C:\\Users\\10954\\Desktop\\MBForge\\src\\mbforge\\model_server\\models\\moldet.py", "source_location": "L17"}, {"caller_nid": "models_moldet_get_moldet", "callee": "gpu_warning", "is_member_call": false, "source_file": "C:\\Users\\10954\\Desktop\\MBForge\\src\\mbforge\\model_server\\models\\moldet.py", "source_location": "L18"}, {"caller_nid": "models_moldet_get_moldet", "callee": "load_global_config", "is_member_call": false, "source_file": "C:\\Users\\10954\\Desktop\\MBForge\\src\\mbforge\\model_server\\models\\moldet.py", "source_location": "L20"}]}